langchain_qualcomm_inference_suite/__init__.py
langchain_qualcomm_inference_suite/chat_models.py
langchain_qualcomm_inference_suite/chat_models_nocommit.py
langchain_qualcomm_inference_suite/embeddings.py
langchain_qualcomm_inference_suite/llms.py
langchain_qualcomm_inference_suite/mixins.py
langchain_qualcomm_inference_suite/py.typed
langchain_qualcomm_inference_suite-1.0.0.dist-info/LICENSE
langchain_qualcomm_inference_suite-1.0.0.dist-info/METADATA
langchain_qualcomm_inference_suite-1.0.0.dist-info/WHEEL
langchain_qualcomm_inference_suite-1.0.0.dist-info/RECORD
