Metadata-Version: 2.3
Name: langchain-qualcomm-inference-suite
Version: 1.0.0
Summary: An integration package connecting Qualcomm AI Inference Suite and LangChain
License: BSD-3-Clause-Clear
Keywords: qualcomm,ai,inference,generative,langchain
Author: Qualcomm Innovation Center, Inc
Author-email: quic.opensource@quicinc.com
Maintainer: Sergi Pons Freixes
Maintainer-email: sponsfre@qti.qualcomm.com
Requires-Python: >=3.9
Classifier: License :: Other/Proprietary License
Classifier: Programming Language :: Python :: 3
Classifier: Programming Language :: Python :: 3.9
Classifier: Programming Language :: Python :: 3.10
Classifier: Programming Language :: Python :: 3.11
Classifier: Programming Language :: Python :: 3.12
Classifier: Programming Language :: Python :: 3.13
Requires-Dist: langchain-core (>=0.3.15,<0.4.0)
Requires-Dist: python-imagine-sdk (>=0.5.0)
Project-URL: Repository, https://github.com/qualcomm/langchain-qualcomm-inference-suite
